ngen_argoapi/__init__.py
ngen_argoapi/argocd.py
ngen_argoapi/cli.py
ngen_argoapi/server.py
ngen_argoapi/__pycache__/__init__.cpython-310.pyc
ngen_argoapi/__pycache__/argocd.cpython-310.pyc
ngen_argoapi/__pycache__/cli.cpython-310.pyc
ngen_argoapi/__pycache__/server.cpython-310.pyc
ngen_argoapi-0.1.15.dist-info/licenses/LICENSE
ngen_argoapi-0.1.15.dist-info/METADATA
ngen_argoapi-0.1.15.dist-info/WHEEL
ngen_argoapi-0.1.15.dist-info/entry_points.txt
ngen_argoapi-0.1.15.dist-info/top_level.txt
ngen_argoapi-0.1.15.dist-info/RECORD
