Metadata-Version: 2.4
Name: ngen-argoapi
Version: 0.1.15
Summary: ArgoCD API management CLI and wrapper package
Author: ngen-argoapi contributors
License-Expression: MIT
Project-URL: Homepage, https://github.com/mamatnurahmat/ngen-argoapi
Project-URL: Repository, https://github.com/mamatnurahmat/ngen-argoapi
Project-URL: Issues, https://github.com/mamatnurahmat/ngen-argoapi/issues
Keywords: cli,wrapper,command,argocd,api,gitops
Classifier: Development Status :: 3 - Alpha
Classifier: Intended Audience :: Developers
Classifier: Programming Language :: Python :: 3
Classifier: Programming Language :: Python :: 3.7
Classifier: Programming Language :: Python :: 3.8
Classifier: Programming Language :: Python :: 3.9
Classifier: Programming Language :: Python :: 3.10
Classifier: Programming Language :: Python :: 3.11
Requires-Python: >=3.7
License-File: LICENSE
Requires-Dist: httpx>=0.23.0
Requires-Dist: python-dotenv>=0.20.0
Requires-Dist: fastapi>=0.100.0
Requires-Dist: uvicorn>=0.20.0
Dynamic: license-file
